az_blob_stacio/__init__.py
az_blob_stacio/az_blob_stacio.py
az_blob_stacio-0.1.2.dist-info/LICENSE
az_blob_stacio-0.1.2.dist-info/METADATA
az_blob_stacio-0.1.2.dist-info/WHEEL
az_blob_stacio-0.1.2.dist-info/top_level.txt
az_blob_stacio-0.1.2.dist-info/RECORD
