Metadata-Version: 2.1
Name: az-blob-stacio
Version: 0.1.2
Summary: An implementation of `pystac`'s `StacIO` for reading static STACs stored in Azure Blob Storage.
Author-email: Brendan McAndrew <brendan.mcandrew.88@gmail.com>
Project-URL: Homepage, https://github.com/bmcandr/az-blob-stacio
Project-URL: Repository, https://github.com/bmcandr/az-blob-stacio.git
Classifier: Intended Audience :: Developers
Classifier: License :: OSI Approved :: Apache Software License
Classifier: Natural Language :: English
Classifier: Programming Language :: Python :: 3
Classifier: Programming Language :: Python :: 3.10
Classifier: Programming Language :: Python :: 3.11
Classifier: Programming Language :: Python :: 3.12
Requires-Python: >=3.10
License-File: LICENSE
Requires-Dist: azure-storage-blob >=12.23.1
Requires-Dist: pystac >=1.11.0
